passthrough_support_excludeglob_fs/__init__.py
passthrough_support_excludeglob_fs/logginng_mixin.py
passthrough_support_excludeglob_fs/main.py
passthrough_support_excludeglob_fs-1.17.dist-info/LICENCE
passthrough_support_excludeglob_fs-1.17.dist-info/METADATA
passthrough_support_excludeglob_fs-1.17.dist-info/WHEEL
passthrough_support_excludeglob_fs-1.17.dist-info/entry_points.txt
passthrough_support_excludeglob_fs-1.17.dist-info/top_level.txt
passthrough_support_excludeglob_fs-1.17.dist-info/RECORD
