Metadata-Version: 2.1
Name: passthrough_support_excludeglob_fs
Version: 1.17
Summary: A user-space filesystem that allows to exclude files from being shown in the filesystem using glob patterns
Home-page: https://github.com/AntonyDalmiere/passthrough_support_globexclude_fuse_fs
Author: Antony Dalmiere
Author-email: zbkk9jrxo@mozmail.com
License: CC BY-NC-NDA 4.0
Keywords: fuse,filesystem,passthrough,excludeglob
Classifier: Development Status :: 4 - Beta
Classifier: Programming Language :: Python :: 3.6
Classifier: Programming Language :: Python :: 3.7
Classifier: Programming Language :: Python :: 3.8
Classifier: Programming Language :: Python :: 3.9
Classifier: Environment :: Console
Classifier: Intended Audience :: System Administrators
Classifier: Operating System :: MacOS
Classifier: Operating System :: POSIX
Classifier: Operating System :: Microsoft :: Windows
Classifier: Operating System :: Unix
Classifier: Topic :: System :: Filesystems
License-File: LICENCE
Requires-Dist: refuse==0.0.4
Requires-Dist: globmatch==2.0.0
Requires-Dist: appdirs==1.4.4
Requires-Dist: psutil==6.0.0
Requires-Dist: str2type==0.4.1
Requires-Dist: syslog2==0.5.0
Requires-Dist: pylnk3==0.4.2
